{
    "Pages": [
        {
            "Page": "https://hack.me/00",
            "Response": 200,
            "children": []
        },
        {
            "Page": "https://hack.me/01",
            "Response": 200,
            "children": []
        },
        {
            "Page": "https://hack.me/02",
            "Response": 200,
            "children": []
        },
        {
            "Page": "https://hack.me/03",
            "Response": 200,
            "children": []
        },
        {
            "Page": "https://hack.me/10",
            "Response": 200,
            "children": []
        },
        {
            "Page": "https://hack.me/100",
            "Response": 200,
            "children": []
        },
        {
            "Page": "https://hack.me/1000",
            "Response": 200,
            "children": []
        },
        {
            "Page": "https://hack.me/101",
            "Response": 200,
            "children": []
        },
        {
            "Page": "https://hack.me/102",
            "Response": 200,
            "children": []
        },
        {
            "Page": "https://hack.me/103",
            "Response": 200,
            "children": []
        },
        {
            "Page": "https://hack.me/1998",
            "Response": 200,
            "children": []
        },
        {
            "Page": "https://hack.me/1999",
            "Response": 200,
            "children": []
        },
        {
            "Page": "https://hack.me/20",
            "Response": 200,
            "children": []
        },
        {
            "Page": "https://hack.me/200",
            "Response": 200,
            "children": []
        },
        {
            "Page": "https://hack.me/2000",
            "Response": 200,
            "children": []
        },
        {
            "Page": "https://hack.me/2001",
            "Response": 200,
            "children": []
        },
        {
            "Page": "https://hack.me/2002",
            "Response": 200,
            "children": []
        },
        {
            "Page": "https://hack.me/2003",
            "Response": 200,
            "children": []
        },
        {
            "Page": "https://hack.me/2004",
            "Response": 200,
            "children": []
        },
        {
            "Page": "https://hack.me/2005",
            "Response": 200,
            "children": []
        },
        {
            "Page": "https://hack.me/2006",
            "Response": 200,
            "children": []
        },
        {
            "Page": "https://hack.me/2007",
            "Response": 200,
            "children": []
        },
        {
            "Page": "https://hack.me/30",
            "Response": 200,
            "children": []
        },
        {
            "Page": "https://hack.me/300",
            "Response": 200,
            "children": []
        },
        {
            "Page": "https://hack.me/About",
            "Response": 200,
            "children": []
        },
        {
            "Page": "https://hack.me/FAQ",
            "Response": 200,
            "children": []
        },
        {
            "Page": "https://hack.me/Images",
            "Response": 403,
            "children": []
        },
        {
            "Page": "https://hack.me/about",
            "Response": 200,
            "children": []
        },
        {
            "Page": "https://hack.me/assets",
            "Response": 403,
            "children": []
        },
        {
            "Page": "https://hack.me/auth",
            "Response": 403,
            "children": []
        },
        {
            "Page": "https://hack.me/b1",
            "Response": 200,
            "children": []
        },
        {
            "Page": "https://hack.me/backend",
            "Response": 403,
            "children": []
        },
        {
            "Page": "https://hack.me/faq",
            "Response": 200,
            "children": []
        },
        {
            "Page": "https://hack.me/favicon.ico",
            "Response": 200,
            "children": []
        },
        {
            "Page": "https://hack.me/images",
            "Response": 403,
            "children": []
        },
        {
            "Page": "https://hack.me/include",
            "Response": 403,
            "children": []
        },
        {
            "Page": "https://hack.me/js",
            "Response": 403,
            "children": []
        },
        {
            "Page": "https://hack.me/libs",
            "Response": 403,
            "children": []
        },
        {
            "Page": "https://hack.me/m1",
            "Response": 200,
            "children": []
        },
        {
            "Page": "https://hack.me/newsletter",
            "Response": 403,
            "children": []
        },
        {
            "Page": "https://hack.me/r57",
            "Response": 200,
            "children": []
        },
        {
            "Page": "https://hack.me/s1",
            "Response": 200,
            "children": []
        },
        {
            "Page": "https://hack.me/t1",
            "Response": 200,
            "children": []
        },
        {
            "Page": "https://hack.me/v2",
            "Response": 200,
            "children": []
        },
        {
            "Page": "https://hack.me/w3",
            "Response": 200,
            "children": []
        }
    ]
}