{
    "ServiceScan": [
        {
            "Name": "Microsoft ASP.NET",
            "Version": [
                "4.0.30319"
            ]
        },
        {
            "Name": "jQuery",
            "Version": [
                "1.11.3",
                "1.12.4"
            ]
        },
        {
            "Name": "IIS",
            "Version": [
                "7.5"
            ]
        },
        {
            "Name": "Windows Server",
            "Version": []
        },
        {
            "Name": "Bootstrap",
            "Version": [
                "3.3.7"
            ]
        },
        {
            "Name": "AngularJS",
            "Version": []
        },
        {
            "Name": "Google Font API",
            "Version": []
        },
        {
            "Name": "Font Awesome",
            "Version": []
        },
        {
            "Name": "Microsoft ASP.NET",
            "Version": [
                "4.0.30319"
            ]
        },
        {
            "Name": "jQuery",
            "Version": [
                "1.11.3"
            ]
        },
        {
            "Name": "Windows Server",
            "Version": []
        },
        {
            "Name": "IIS",
            "Version": [
                "7.5"
            ]
        },
        {
            "Name": "Bootstrap",
            "Version": [
                "3.3.7"
            ]
        },
        {
            "Name": "reCAPTCHA",
            "Version": []
        },
        {
            "Name": "jQuery UI",
            "Version": [
                "1.12.1"
            ]
        },
        {
            "Name": "Google Font API",
            "Version": []
        },
        {
            "Name": "Font Awesome",
            "Version": []
        },
        {
            "Name": "AngularJS",
            "Version": []
        },
        {
            "Name": "Fingerprintjs",
            "Version": [
                "1.5.1"
            ]
        },
        {
            "Name": "Font Awesome",
            "Version": [
                "4.3.0"
            ]
        },
        {
            "Name": "Bootstrap",
            "Version": []
        },
        {
            "Name": "Google Font API",
            "Version": []
        },
        {
            "Name": "jQuery",
            "Version": [
                "1.12.4"
            ]
        },
        {
            "Name": "Microsoft ASP.NET",
            "Version": []
        }
    ]
}